haven_python_client/__init__.py
haven_python_client/main.py
haven_python_client-0.4.0.dist-info/METADATA
haven_python_client-0.4.0.dist-info/WHEEL
haven_python_client-0.4.0.dist-info/top_level.txt
haven_python_client-0.4.0.dist-info/RECORD
